database_automation/__init__.py
database_automation/mongo_crud.py
devdbautomation-0.1.0.dist-info/METADATA
devdbautomation-0.1.0.dist-info/WHEEL
devdbautomation-0.1.0.dist-info/top_level.txt
devdbautomation-0.1.0.dist-info/RECORD
